README.rst
setup.py
medcon/__init__.py
medcon/medcon.py
medcon.egg-info/PKG-INFO
medcon.egg-info/SOURCES.txt
medcon.egg-info/dependency_links.txt
medcon.egg-info/not-zip-safe
medcon.egg-info/requires.txt
medcon.egg-info/top_level.txt