Metadata-Version: 1.0
Name: medcon
Version: 1.1.0.0
Summary: A ChRIS DS plugin that wraps around medcon and provides NifTI to DICOM conversion capability.
Home-page: https://github.com/FNNDSC/pl-medcon
Author: Arushi Vyas / Rudolph Pienaar
Author-email: dev@babyMRI.org
License: MIT
Platform: UNKNOWN
